Jira/__init__.py
Jira/jira_api.py
atlassian_cloud-0.0.1.dist-info/METADATA
atlassian_cloud-0.0.1.dist-info/WHEEL
atlassian_cloud-0.0.1.dist-info/top_level.txt
atlassian_cloud-0.0.1.dist-info/RECORD
