Metadata-Version: 2.1
Name: atlassian-cloud
Version: 0.0.1
Summary: Python module for Atlassian Cloud REST API
Home-page: UNKNOWN
Author: Régis Tremblay Lefrancois
Author-email: rtlefrancois@agri-marche.com
License: UNKNOWN
Platform: UNKNOWN
Classifier: Programming Language :: Python :: 3
Classifier: License :: OSI Approved :: MIT License
Classifier: Operating System :: OS Independent
Requires-Python: >=3.6
Requires-Dist: requests (>=2.23.0)
